pyhub/__init__.py
pyhub/mcp_tools/__init__.py
pyhub/mcp_tools/__main__.py
pyhub/mcp_tools/browser/__init__.py
pyhub/mcp_tools/browser/__main__.py
pyhub/mcp_tools/browser/apps.py
pyhub/mcp_tools/browser/tools.py
pyhub/mcp_tools/core/__init__.py
pyhub/mcp_tools/core/apps.py
pyhub/mcp_tools/core/choices.py
pyhub/mcp_tools/core/cli.py
pyhub/mcp_tools/core/init.py
pyhub/mcp_tools/core/routers.py
pyhub/mcp_tools/core/settings.py
pyhub/mcp_tools/core/utils.py
pyhub/mcp_tools/excel/__init__.py
pyhub/mcp_tools/excel/__main__.py
pyhub/mcp_tools/excel/apps.py
pyhub/mcp_tools/excel/tools.py
pyhub/mcp_tools/excel/types.py
pyhub/mcp_tools/setup/__init__.py
pyhub/mcp_tools/setup/__main__.py
pyhub/mcp_tools/setup/apps.py
pyhub/mcp_tools/setup/choices.py
pyhub/mcp_tools/setup/tools.py
pyhub/mcp_tools/setup/utils.py
pyhub_mcp_tools-0.2.0.dist-info/METADATA
pyhub_mcp_tools-0.2.0.dist-info/WHEEL
pyhub_mcp_tools-0.2.0.dist-info/entry_points.txt
pyhub_mcp_tools-0.2.0.dist-info/RECORD
